{
    "General": "- Bots will now replace a human player if the player has been disconnected for more than 30 seconds (hero will retreat home first and then after 30 seconds the bot takes over). After 4 minutes it will start using souls to buy items. During laning phase it will go to its assigned lane, afterwards it will aim to stick near where most allies are located. If the player rejoins the bot will leave. We will work on improving the bot behavior as we get feedback.\n- Added a temporary matchmaking ban system for people that leave games\n- Reworked the Watch tab to highlight suggested matches to watch. There is currently a limit on the number of people that can watch the same match, so it'll recommend different games if the best suggestions are full. We are working on removing the spectator limit for a future update.\n- Matches in the watch tab will now indicate if a friend is in that match\n- A paused a game can only be unpaused by the player that paused for the first 30 seconds\n- Once you pause a game, you cannot pause it again within 5 minutes\n- Pause now says the player name pausing it\n- Added a view cone for your player on the minimap to help with finding yourself and the direction you are pointed\n- Added a sound when you receive a chat message\n- Increased the base font size for text chat\n- Increased the duration text chat is visible\n- You can now ping enemy items on the scoreboard to say alert players that the hero has that item.\n- You can now middle mouse click an ability to say its on cooldown\n- You can now alt click your active items to say if they are ready or not\n- Candle Troopers and other NPCS can no longer see or shoot through Cosmic Veils\n- Changed F1-F5 keys to instantly snap to the team mates rather than move there more slowly\n- Adjusted the health bar on Walkers to be easier to see\n- Match found sound now plays regardless of window focus\n- Added option to give fast stamina regen in Hero Sandbox\n- Minimap player icons now dynamically shrink and adjust positions slightly when there are many overlapping\n- Fixed zooming bypassing the shooting speed penalty\n- Added new effects for Shifting Shroud\n- T1 Boss now has quicker melee animations\n- Fixed Turrets causing backdoor protection to be lost\n- Fixed {{Icon|Guided Owl}} Guided Owl flying while the game is paused\n- Fixed a bug with using Melee in the air that could cause you to move a lot\n- Fixed some sound issues with {{Icon|{{Icon|Pulse}} Pulse Grenade}} {{Icon|Pulse}} Pulse Grenade\n- Added new sprint animations for {{Icon|Abrams}} Abrams\n- Various fixes to {{Icon|Lash}} Lash's {{Icon|Ground Strike}} Ground Strike visual effects\n- Fixed various bugs and crashes with hero guides\n- Fixed Turrets not proccing things like {{Icon|Mystic Vulnerability}} Mystic Vulnerability\n- Fixed some outdated details on the minimap\n- {{Icon|Grey Talon}} Grey Talon's {{Icon|Charged Shot}} Charged Shot effect matches the damage radius better\n- Added visual tell for when {{Icon|Assassinate}} Assassinate is active\n- Fixed some bugs that could cause {{Icon|McGinnis}} McGinnis gun to be stuck\n- Updated Zipline Boost hint to say ACTIVE when it is active and only show the cooldown timer when its done\n- Fixed an edge case with {{Icon|Unstoppable}} Unstoppable and a debuff being applied on the same frame\n- Reduced minimum delay before you can press a button again to cancel a channel/precast from 0.5 to 0.2\n- Fixed getting stuck going up the ramp on the inner lane street\n- Fixed corner neutral camps not burrowing if they lose line of sight\n- Fixed being able to get on top of the tall border building behind the Chapel and behind the Firehouse\n[Misc Gameplay]\n- Lane Guardian HP increased from 3750 to 4600\n- Various adjustments to lane layout to give defenders more options for forward positions near their Guardian\n- Midlane Walkers HP reduced a little bit to match the same HP as the sidelane Walkers\n- Base Guardians moved a little bit further towards the outside of the base\n- Airborne Heavy Melee now triggers when the charge up is complete, rather than waiting for the player to land on the ground (you had to manually release it before)\n- Airborne Heavy Melee distance increased to match ground version\n- Heavy Melee time reduced from 0.6 to 0.55 (same for Air)\n- Crate powerups can now only spawn after 2 minutes (when the small neutrals spawn)\n- Added breakable crates inside each lane's Cosmic Veil\n- Expanded space in some of the lane's Cosmic Veils\n- Audible distance of enemy footsteps is reduced\n- Special 15 minute melee creep now upgrades again at 25 minutes\n- Base zipline speed increased by 10%\n- Extended inner lane urn bridge buildings toward the T1 and added a doorway to allow defenders to shoot down into the canal\n- Removed 3 bush trees on each inner lane near the urn bridge buildings\n- Carved out interior of inner lane tower buildings beside the Guardian and connected to the neutral camp in the underground areas\n- Moved outer lane Walker on Factory and Mansion sides slightly closer to the stairs\n- Carved out interior of outer lane wall buildings beside the Walker to allow forward position for defenders\n- Reduced width of forward base lookout bridges\n[Item Gameplay]\n- Ammo reduced from +16% to +15%\n- Weapon Damage reduced from +16% to +15%\n- Cooldown reduced from 9s to 5s\n- Health Regen increased from 0.7 to 1\n- No longer provides +1 Sprint\n- +10% {{Icon|Spirit Lifesteal}} Spirit Lifesteal\n- Spirit Amp reduced from 14% to 12%\n- Cooldown increased from 25 to 27\n- Spirit increased from +4 to +5\n- Cast range now scales with Spirit (0.2 factor)\n- Fire rate slow increased from 30% to 35%\n- Move Speed increased from +1.25 to +1.4\n- Bullet Resist penalty reduced from -8% to -7%\n- Now grants +5 Spirit\n- Bullet Shield Health increased from +150 to +175\n- Cooldown reduced from 37 to 34\n- Shifting Shroud: Duration increased from 2.75 to 3\n- Shifting Shroud: Can now be canceled early\n- Shifting Shroud: Cooldown reduced from 55s to 45s\n- Cooldown reduced from 50s to 40s\n- Spirit buff duration increased from 8s to 12s\n- Melee damage increased from +35% to +40%\n- Now deals half damage against troopers and neutrals\n- No longer gives +8 Spirit\n- Weapon Damage reduced from +70% to +65%\n- No longer stops the echo if the target dies\n- Duration reduced from 5s to 4.5s\n- Lifesteal increased from 60% to 70%\n- Invis Sprint increased from +3 to +5\n- Now grants +8 Spirit\n- Spirit Resist increased from +10% to +12%\n- Ammo increased from +15% to +20%\n- Spirit bonus increased from 30 to 35\n- Spirit increased from +40 to +45\n[Hero Gameplay]\n- {{Icon|Seismic Impact}} Seismic Impact is now faster to play out\n- {{Icon|Seismic Impact}} Seismic Impact now has a very brief busy state upon landing\n- Hyperbeam width increased from 2.7m to 2.9m\n- Base bullet armor increased from 20% to 24%\n- {{Icon|Quantum Entanglement}} Quantum Entanglement fire rate bonus reduced from 35% to 30%\n- {{Icon|Singularity}} Singularity T1 range increased from +2m to +3m\n- Charge Shot spirit scaling improved from 1 to 1.3\n- {{Icon|Guided Owl}} Guided Owl duration increased from 13s to 14s\n- {{Icon|Guided Owl}} Guided Owl T3 increased from 20% to 22%\n- {{Icon|Guided Owl}} Guided Owl player collision sized increased to regular sizes for these kind of projectiles\n- {{Icon|Sleep Dagger}} Sleep Dagger cooldown increased from 27 to 29\n- {{Icon|Sleep Dagger}} Sleep Dagger spirit scaling increased from 2.2 to 2.5\n- {{Icon|Smoke Bomb}} Smoke Bomb T2 and T3 swapped\n- {{Icon|Smoke Bomb}} Smoke Bomb T3 cooldown improved from -20s to -25s\n- {{Icon|Afterburn}} Afterburn T3 reduced from +40 dps to +35\n- {{Icon|Flame Dash}} Flame Dash T1 duration reduced from 8s to 7s\n- {{Icon|Flame Dash}} Flame Dash T1 Fire Rate slow increased from +30% to +35%\n- {{Icon|Flame Dash}} Flame Dash T2 increased from +40 DPS to +45\n- {{Icon|Flame Dash}} Flame Dash T3 increased from -15s to -20s\n- {{Icon|Kudzu Bomb}} Kudzu Bomb T3 improved from +50 DPS to +60\n- Base health increased from 550 to 600\n- {{Icon|Frost Grenade}} Frost Grenade radius increased from 6 to 6.5\n- {{Icon|Frost Grenade}} Frost Grenade charge time reduced from 10s to 8s\n- Players can now slide down the {{Icon|Ice Path}} Ice Path\n- {{Icon|Ice Path}} Ice Path slow resistance increased from 50% to 60%\n- {{Icon|Ice Path}} Ice Path T3 max spirit increased from 40 to 55\n- {{Icon|Soul Exchange}} Soul Exchange cast time reduced from 0.5 to 0.2\n- Rocket {{Icon|Barrage}} Barrage now does less damage to objectives similar to other ability damage\n- {{Icon|Sand Blast}} Sand Blast no longer affects bosses\n- Bullet base damage reduced from 8 to 7.2 (indirectly affects {{Icon|Kinetic Carbine}} Kinetic Carbine)\n- Bullet growth reduced from 0.48 to 0.42 (indirectly affects {{Icon|Kinetic Carbine}} Kinetic Carbine)\n- {{Icon|Kinetic Carbine}} Kinetic Carbine damage reduced from +100% to +85%\n- {{Icon|Paradox}} {{Icon|Paradoxical Swap}} Paradoxical Swap range reduced from 40m to 35m\n- Fixed {{Icon|Paradox}} {{Icon|Paradoxical Swap}} Paradoxical Swap being able to grab multiple heroes if they were really close to each other\n- {{Icon|Barrage}} Barrage radius increased from 5m to 6m\n- {{Icon|Barrage}} Barrage cooldown reduced from 35 to 30\n- {{Icon|Barrage}} Barrage T3 increased from 100% to 150%\n- {{Icon|Flying Cloak}} Flying Cloak speed increased by 7%\n- {{Icon|Flying Cloak}} Flying Cloak T3 increased from +5 damage to +7\n- Now has -10% Base Bullet Resist\n- {{Icon|Flight}} Flight no longer grants +1 bonus air speed\n- {{Icon|Flight}} Flight falloff damage increase reduced from +20% to +10%\n- Fixed flight spirit damage being able to pierce {{Icon|Metal Skin}} Metal Skin\n- {{Icon|Willpower}} Willpower T1 improved from +15% to +20%\n- {{Icon|Last Stand}} Last Stand duration increased from 5s to 6s\n- {{Icon|Project Mind}} Project Mind cooldown reduced from 50s to 45s\n- {{Icon|Power Slash}} Power Slash spirit scaling improved from 1.6 to 2.0\n- {{Icon|Power Slash}} Power Slash no longer does a very minor movement on enemies hit\n- Fixed {{Icon|Power Slash}} Power Slash sometimes not being a full charge when channeled fully during the {{Icon|Shadow Transformation}} Shadow Transformation\n- {{Icon|Shadow Transformation}} Shadow Transformation's ability speedup now affects the post-cast durations as well\n- {{Icon|Shadow Transformation}} Shadow Transformation's ability speedup now improves the visual animations (cosmetic only change)\n",
    "Flying Cloak": "- {{Icon|Flying Cloak}} Flying Cloak speed increased by 7%\n- {{Icon|Flying Cloak}} Flying Cloak T3 increased from +5 damage to +7\n",
    "Abilities": "- Fixed {{Icon|Guided Owl}} Guided Owl flying while the game is paused\n- Fixed some sound issues with {{Icon|{{Icon|Pulse}} Pulse Grenade}} {{Icon|Pulse}} Pulse Grenade\n- Various fixes to {{Icon|Lash}} Lash's {{Icon|Ground Strike}} Ground Strike visual effects\n- {{Icon|Grey Talon}} Grey Talon's {{Icon|Charged Shot}} Charged Shot effect matches the damage radius better\n- Added visual tell for when {{Icon|Assassinate}} Assassinate is active\n- {{Icon|Seismic Impact}} Seismic Impact is now faster to play out\n- {{Icon|Seismic Impact}} Seismic Impact now has a very brief busy state upon landing\n- {{Icon|Quantum Entanglement}} Quantum Entanglement fire rate bonus reduced from 35% to 30%\n- {{Icon|Singularity}} Singularity T1 range increased from +2m to +3m\n- {{Icon|Guided Owl}} Guided Owl duration increased from 13s to 14s\n- {{Icon|Guided Owl}} Guided Owl T3 increased from 20% to 22%\n- {{Icon|Guided Owl}} Guided Owl player collision sized increased to regular sizes for these kind of projectiles\n- {{Icon|Sleep Dagger}} Sleep Dagger cooldown increased from 27 to 29\n- {{Icon|Sleep Dagger}} Sleep Dagger spirit scaling increased from 2.2 to 2.5\n- {{Icon|Smoke Bomb}} Smoke Bomb T2 and T3 swapped\n- {{Icon|Smoke Bomb}} Smoke Bomb T3 cooldown improved from -20s to -25s\n- {{Icon|Afterburn}} Afterburn T3 reduced from +40 dps to +35\n- {{Icon|Flame Dash}} Flame Dash T1 duration reduced from 8s to 7s\n- {{Icon|Flame Dash}} Flame Dash T1 Fire Rate slow increased from +30% to +35%\n- {{Icon|Flame Dash}} Flame Dash T2 increased from +40 DPS to +45\n- {{Icon|Flame Dash}} Flame Dash T3 increased from -15s to -20s\n- {{Icon|Kudzu Bomb}} Kudzu Bomb T3 improved from +50 DPS to +60\n- {{Icon|Frost Grenade}} Frost Grenade radius increased from 6 to 6.5\n- {{Icon|Frost Grenade}} Frost Grenade charge time reduced from 10s to 8s\n- Players can now slide down the {{Icon|Ice Path}} Ice Path\n- {{Icon|Ice Path}} Ice Path slow resistance increased from 50% to 60%\n- {{Icon|Ice Path}} Ice Path T3 max spirit increased from 40 to 55\n- {{Icon|Soul Exchange}} Soul Exchange cast time reduced from 0.5 to 0.2\n- Rocket {{Icon|Barrage}} Barrage now does less damage to objectives similar to other ability damage\n- {{Icon|Sand Blast}} Sand Blast no longer affects bosses\n- Bullet base damage reduced from 8 to 7.2 (indirectly affects {{Icon|Kinetic Carbine}} Kinetic Carbine)\n- Bullet growth reduced from 0.48 to 0.42 (indirectly affects {{Icon|Kinetic Carbine}} Kinetic Carbine)\n- {{Icon|Kinetic Carbine}} Kinetic Carbine damage reduced from +100% to +85%\n- {{Icon|Paradox}} {{Icon|Paradoxical Swap}} Paradoxical Swap range reduced from 40m to 35m\n- Fixed {{Icon|Paradox}} {{Icon|Paradoxical Swap}} Paradoxical Swap being able to grab multiple heroes if they were really close to each other\n- {{Icon|Barrage}} Barrage radius increased from 5m to 6m\n- {{Icon|Barrage}} Barrage cooldown reduced from 35 to 30\n- {{Icon|Barrage}} Barrage T3 increased from 100% to 150%\n- {{Icon|Flying Cloak}} Flying Cloak speed increased by 7%\n- {{Icon|Flying Cloak}} Flying Cloak T3 increased from +5 damage to +7\n- {{Icon|Flight}} Flight no longer grants +1 bonus air speed\n- {{Icon|Flight}} Flight falloff damage increase reduced from +20% to +10%\n- {{Icon|Willpower}} Willpower T1 improved from +15% to +20%\n- {{Icon|Last Stand}} Last Stand duration increased from 5s to 6s\n- {{Icon|Project Mind}} Project Mind cooldown reduced from 50s to 45s\n- {{Icon|Power Slash}} Power Slash spirit scaling improved from 1.6 to 2.0\n- {{Icon|Power Slash}} Power Slash no longer does a very minor movement on enemies hit\n- Fixed {{Icon|Power Slash}} Power Slash sometimes not being a full charge when channeled fully during the {{Icon|Shadow Transformation}} Shadow Transformation\n- {{Icon|Shadow Transformation}} Shadow Transformation's ability speedup now affects the post-cast durations as well\n- {{Icon|Shadow Transformation}} Shadow Transformation's ability speedup now improves the visual animations (cosmetic only change)\n",
    "Items": "- Fixed Turrets not proccing things like {{Icon|Mystic Vulnerability}} Mystic Vulnerability\n- Fixed an edge case with {{Icon|Unstoppable}} Unstoppable and a debuff being applied on the same frame\n- Ammo reduced from +16% to +15%\n- Weapon Damage reduced from +16% to +15%\n- Cooldown reduced from 9s to 5s\n- Health Regen increased from 0.7 to 1\n- No longer provides +1 Sprint\n- +10% {{Icon|Spirit Lifesteal}} Spirit Lifesteal\n- Spirit Amp reduced from 14% to 12%\n- Cooldown increased from 25 to 27\n- Spirit increased from +4 to +5\n- Cast range now scales with Spirit (0.2 factor)\n- Fire rate slow increased from 30% to 35%\n- Move Speed increased from +1.25 to +1.4\n- Bullet Resist penalty reduced from -8% to -7%\n- Now grants +5 Spirit\n- Bullet Shield Health increased from +150 to +175\n- Cooldown reduced from 37 to 34\n- Cooldown reduced from 50s to 40s\n- Spirit buff duration increased from 8s to 12s\n- Melee damage increased from +35% to +40%\n- Now deals half damage against troopers and neutrals\n- No longer gives +8 Spirit\n- Weapon Damage reduced from +70% to +65%\n- No longer stops the echo if the target dies\n- Duration reduced from 5s to 4.5s\n- Lifesteal increased from 60% to 70%\n- Invis Sprint increased from +3 to +5\n- Now grants +8 Spirit\n- Spirit Resist increased from +10% to +12%\n- Ammo increased from +15% to +20%\n- Spirit bonus increased from 30 to 35\n- Spirit increased from +40 to +45\n- Fixed flight spirit damage being able to pierce {{Icon|Metal Skin}} Metal Skin\n",
    "Weapon Items": "- Ammo reduced from +16% to +15%\n- Weapon Damage reduced from +16% to +15%\n- Cooldown reduced from 9s to 5s\n- Spirit Amp reduced from 14% to 12%\n- Bullet Resist penalty reduced from -8% to -7%\n- Now grants +5 Spirit\n- Bullet Shield Health increased from +150 to +175\n- Cooldown reduced from 37 to 34\n- Now deals half damage against troopers and neutrals\n- Weapon Damage reduced from +70% to +65%\n- Duration reduced from 5s to 4.5s\n- Lifesteal increased from 60% to 70%\n- Invis Sprint increased from +3 to +5\n- Ammo increased from +15% to +20%\n- Spirit bonus increased from 30 to 35\n",
    "Yamato": "- {{Icon|Power Slash}} Power Slash spirit scaling improved from 1.6 to 2.0\n- {{Icon|Power Slash}} Power Slash no longer does a very minor movement on enemies hit\n- Fixed {{Icon|Power Slash}} Power Slash sometimes not being a full charge when channeled fully during the {{Icon|Shadow Transformation}} Shadow Transformation\n- {{Icon|Shadow Transformation}} Shadow Transformation's ability speedup now affects the post-cast durations as well\n- {{Icon|Shadow Transformation}} Shadow Transformation's ability speedup now improves the visual animations (cosmetic only change)\n",
    "Heroes": "- Added new sprint animations for {{Icon|Abrams}} Abrams\n- Various fixes to {{Icon|Lash}} Lash's {{Icon|Ground Strike}} Ground Strike visual effects\n- {{Icon|Grey Talon}} Grey Talon's {{Icon|Charged Shot}} Charged Shot effect matches the damage radius better\n- Fixed some bugs that could cause {{Icon|McGinnis}} McGinnis gun to be stuck\n- {{Icon|Seismic Impact}} Seismic Impact is now faster to play out\n- {{Icon|Seismic Impact}} Seismic Impact now has a very brief busy state upon landing\n- Hyperbeam width increased from 2.7m to 2.9m\n- Base bullet armor increased from 20% to 24%\n- {{Icon|Quantum Entanglement}} Quantum Entanglement fire rate bonus reduced from 35% to 30%\n- {{Icon|Singularity}} Singularity T1 range increased from +2m to +3m\n- Charge Shot spirit scaling improved from 1 to 1.3\n- {{Icon|Guided Owl}} Guided Owl duration increased from 13s to 14s\n- {{Icon|Guided Owl}} Guided Owl T3 increased from 20% to 22%\n- {{Icon|Guided Owl}} Guided Owl player collision sized increased to regular sizes for these kind of projectiles\n- {{Icon|Sleep Dagger}} Sleep Dagger cooldown increased from 27 to 29\n- {{Icon|Sleep Dagger}} Sleep Dagger spirit scaling increased from 2.2 to 2.5\n- {{Icon|Smoke Bomb}} Smoke Bomb T2 and T3 swapped\n- {{Icon|Smoke Bomb}} Smoke Bomb T3 cooldown improved from -20s to -25s\n- {{Icon|Afterburn}} Afterburn T3 reduced from +40 dps to +35\n- {{Icon|Flame Dash}} Flame Dash T1 duration reduced from 8s to 7s\n- {{Icon|Flame Dash}} Flame Dash T1 Fire Rate slow increased from +30% to +35%\n- {{Icon|Flame Dash}} Flame Dash T2 increased from +40 DPS to +45\n- {{Icon|Flame Dash}} Flame Dash T3 increased from -15s to -20s\n- {{Icon|Kudzu Bomb}} Kudzu Bomb T3 improved from +50 DPS to +60\n- Base health increased from 550 to 600\n- {{Icon|Frost Grenade}} Frost Grenade radius increased from 6 to 6.5\n- {{Icon|Frost Grenade}} Frost Grenade charge time reduced from 10s to 8s\n- Players can now slide down the {{Icon|Ice Path}} Ice Path\n- {{Icon|Ice Path}} Ice Path slow resistance increased from 50% to 60%\n- {{Icon|Ice Path}} Ice Path T3 max spirit increased from 40 to 55\n- {{Icon|Soul Exchange}} Soul Exchange cast time reduced from 0.5 to 0.2\n- Rocket {{Icon|Barrage}} Barrage now does less damage to objectives similar to other ability damage\n- {{Icon|Sand Blast}} Sand Blast no longer affects bosses\n- Bullet base damage reduced from 8 to 7.2 (indirectly affects {{Icon|Kinetic Carbine}} Kinetic Carbine)\n- Bullet growth reduced from 0.48 to 0.42 (indirectly affects {{Icon|Kinetic Carbine}} Kinetic Carbine)\n- {{Icon|Kinetic Carbine}} Kinetic Carbine damage reduced from +100% to +85%\n- {{Icon|Paradox}} {{Icon|Paradoxical Swap}} Paradoxical Swap range reduced from 40m to 35m\n- Fixed {{Icon|Paradox}} {{Icon|Paradoxical Swap}} Paradoxical Swap being able to grab multiple heroes if they were really close to each other\n- {{Icon|Barrage}} Barrage radius increased from 5m to 6m\n- {{Icon|Barrage}} Barrage cooldown reduced from 35 to 30\n- {{Icon|Barrage}} Barrage T3 increased from 100% to 150%\n- {{Icon|Flying Cloak}} Flying Cloak speed increased by 7%\n- {{Icon|Flying Cloak}} Flying Cloak T3 increased from +5 damage to +7\n- Now has -10% Base Bullet Resist\n- {{Icon|Flight}} Flight no longer grants +1 bonus air speed\n- {{Icon|Flight}} Flight falloff damage increase reduced from +20% to +10%\n- Fixed flight spirit damage being able to pierce {{Icon|Metal Skin}} Metal Skin\n- {{Icon|Willpower}} Willpower T1 improved from +15% to +20%\n- {{Icon|Last Stand}} Last Stand duration increased from 5s to 6s\n- {{Icon|Project Mind}} Project Mind cooldown reduced from 50s to 45s\n- {{Icon|Power Slash}} Power Slash spirit scaling improved from 1.6 to 2.0\n- {{Icon|Power Slash}} Power Slash no longer does a very minor movement on enemies hit\n- Fixed {{Icon|Power Slash}} Power Slash sometimes not being a full charge when channeled fully during the {{Icon|Shadow Transformation}} Shadow Transformation\n- {{Icon|Shadow Transformation}} Shadow Transformation's ability speedup now affects the post-cast durations as well\n- {{Icon|Shadow Transformation}} Shadow Transformation's ability speedup now improves the visual animations (cosmetic only change)\n",
    "Abrams": "- Added new sprint animations for {{Icon|Abrams}} Abrams\n- {{Icon|Seismic Impact}} Seismic Impact is now faster to play out\n- {{Icon|Seismic Impact}} Seismic Impact now has a very brief busy state upon landing\n",
    "Bebop": "- Hyperbeam width increased from 2.7m to 2.9m\n- Base bullet armor increased from 20% to 24%\n",
    "Dynamo": "- {{Icon|Quantum Entanglement}} Quantum Entanglement fire rate bonus reduced from 35% to 30%\n- {{Icon|Singularity}} Singularity T1 range increased from +2m to +3m\n",
    "Singularity": "- {{Icon|Singularity}} Singularity T1 range increased from +2m to +3m\n",
    "Grey Talon": "- {{Icon|Grey Talon}} Grey Talon's {{Icon|Charged Shot}} Charged Shot effect matches the damage radius better\n- Charge Shot spirit scaling improved from 1 to 1.3\n- {{Icon|Guided Owl}} Guided Owl duration increased from 13s to 14s\n- {{Icon|Guided Owl}} Guided Owl T3 increased from 20% to 22%\n- {{Icon|Guided Owl}} Guided Owl player collision sized increased to regular sizes for these kind of projectiles\n",
    "Guided Owl": "- Fixed {{Icon|Guided Owl}} Guided Owl flying while the game is paused\n- {{Icon|Guided Owl}} Guided Owl duration increased from 13s to 14s\n- {{Icon|Guided Owl}} Guided Owl T3 increased from 20% to 22%\n- {{Icon|Guided Owl}} Guided Owl player collision sized increased to regular sizes for these kind of projectiles\n",
    "Haze": "- {{Icon|Sleep Dagger}} Sleep Dagger cooldown increased from 27 to 29\n- {{Icon|Sleep Dagger}} Sleep Dagger spirit scaling increased from 2.2 to 2.5\n- {{Icon|Smoke Bomb}} Smoke Bomb T2 and T3 swapped\n- {{Icon|Smoke Bomb}} Smoke Bomb T3 cooldown improved from -20s to -25s\n",
    "Smoke Bomb": "- {{Icon|Smoke Bomb}} Smoke Bomb T2 and T3 swapped\n- {{Icon|Smoke Bomb}} Smoke Bomb T3 cooldown improved from -20s to -25s\n",
    "Infernus": "- {{Icon|Afterburn}} Afterburn T3 reduced from +40 dps to +35\n- {{Icon|Flame Dash}} Flame Dash T1 duration reduced from 8s to 7s\n- {{Icon|Flame Dash}} Flame Dash T1 Fire Rate slow increased from +30% to +35%\n- {{Icon|Flame Dash}} Flame Dash T2 increased from +40 DPS to +45\n- {{Icon|Flame Dash}} Flame Dash T3 increased from -15s to -20s\n",
    "Kelvin": "- Base health increased from 550 to 600\n- {{Icon|Frost Grenade}} Frost Grenade radius increased from 6 to 6.5\n- {{Icon|Frost Grenade}} Frost Grenade charge time reduced from 10s to 8s\n- Players can now slide down the {{Icon|Ice Path}} Ice Path\n- {{Icon|Ice Path}} Ice Path slow resistance increased from 50% to 60%\n- {{Icon|Ice Path}} Ice Path T3 max spirit increased from 40 to 55\n",
    "Frost Grenade": "- {{Icon|Frost Grenade}} Frost Grenade radius increased from 6 to 6.5\n- {{Icon|Frost Grenade}} Frost Grenade charge time reduced from 10s to 8s\n",
    "Lady Geist": "- {{Icon|Soul Exchange}} Soul Exchange cast time reduced from 0.5 to 0.2\n",
    "Lash": "- Various fixes to {{Icon|Lash}} Lash's {{Icon|Ground Strike}} Ground Strike visual effects\n",
    "McGinnis": "- Fixed some bugs that could cause {{Icon|McGinnis}} McGinnis gun to be stuck\n- Rocket {{Icon|Barrage}} Barrage now does less damage to objectives similar to other ability damage\n",
    "Barrage": "- Rocket {{Icon|Barrage}} Barrage now does less damage to objectives similar to other ability damage\n- {{Icon|Barrage}} Barrage radius increased from 5m to 6m\n- {{Icon|Barrage}} Barrage cooldown reduced from 35 to 30\n- {{Icon|Barrage}} Barrage T3 increased from 100% to 150%\n",
    "Mo & Krill": "- {{Icon|Sand Blast}} Sand Blast no longer affects bosses\n",
    "Sand Blast": "- {{Icon|Sand Blast}} Sand Blast no longer affects bosses\n",
    "Vindicta": "- Now has -10% Base Bullet Resist\n- {{Icon|Flight}} Flight no longer grants +1 bonus air speed\n- {{Icon|Flight}} Flight falloff damage increase reduced from +20% to +10%\n- Fixed flight spirit damage being able to pierce {{Icon|Metal Skin}} Metal Skin\n",
    "Power Slash": "- {{Icon|Power Slash}} Power Slash spirit scaling improved from 1.6 to 2.0\n- {{Icon|Power Slash}} Power Slash no longer does a very minor movement on enemies hit\n- Fixed {{Icon|Power Slash}} Power Slash sometimes not being a full charge when channeled fully during the {{Icon|Shadow Transformation}} Shadow Transformation\n",
    "Pocket": "- {{Icon|Barrage}} Barrage radius increased from 5m to 6m\n- {{Icon|Barrage}} Barrage cooldown reduced from 35 to 30\n- {{Icon|Barrage}} Barrage T3 increased from 100% to 150%\n- {{Icon|Flying Cloak}} Flying Cloak speed increased by 7%\n- {{Icon|Flying Cloak}} Flying Cloak T3 increased from +5 damage to +7\n",
    "Vitality Items": "- Fixed an edge case with {{Icon|Unstoppable}} Unstoppable and a debuff being applied on the same frame\n- No longer provides +1 Sprint\n- +10% {{Icon|Spirit Lifesteal}} Spirit Lifesteal\n- Spirit increased from +4 to +5\n- Move Speed increased from +1.25 to +1.4\n- Spirit buff duration increased from 8s to 12s\n- Melee damage increased from +35% to +40%\n- No longer gives +8 Spirit\n- Fixed flight spirit damage being able to pierce {{Icon|Metal Skin}} Metal Skin\n",
    "Quantum Entanglement": "- {{Icon|Quantum Entanglement}} Quantum Entanglement fire rate bonus reduced from 35% to 30%\n",
    "Decay": "- Cast range now scales with Spirit (0.2 factor)\n",
    "Spirit Items": "- Fixed Turrets not proccing things like {{Icon|Mystic Vulnerability}} Mystic Vulnerability\n- Health Regen increased from 0.7 to 1\n- Cooldown increased from 25 to 27\n- Cast range now scales with Spirit (0.2 factor)\n- Fire rate slow increased from 30% to 35%\n- Cooldown reduced from 50s to 40s\n- No longer stops the echo if the target dies\n- Now grants +8 Spirit\n- Spirit Resist increased from +10% to +12%\n- Spirit increased from +40 to +45\n",
    "Restorative Locket": "- Spirit increased from +4 to +5\n",
    "Spirit Strike": "- Health Regen increased from 0.7 to 1\n",
    "Alchemical Fire": "- Now grants +5 Spirit\n- Bullet Shield Health increased from +150 to +175\n- Cooldown reduced from 37 to 34\n",
    "Slowing Hex": "- Cooldown increased from 25 to 27\n",
    "Enduring Speed": "- Move Speed increased from +1.25 to +1.4\n",
    "Suppressor": "- Fire rate slow increased from 30% to 35%\n",
    "Knockdown": "- Cooldown reduced from 50s to 40s\n",
    "Superior Stamina": "- Spirit buff duration increased from 8s to 12s\n",
    "Lifestrike": "- Melee damage increased from +35% to +40%\n",
    "Curse": "- Now grants +8 Spirit\n",
    "Shadow Weave": "- Invis Sprint increased from +3 to +5\n",
    "Vampiric Burst": "- Duration reduced from 5s to 4.5s\n- Lifesteal increased from 60% to 70%\n",
    "Unstoppable": "- Fixed an edge case with {{Icon|Unstoppable}} Unstoppable and a debuff being applied on the same frame\n",
    "Spirit Lifesteal": "- +10% {{Icon|Spirit Lifesteal}} Spirit Lifesteal\n",
    "Mystic Reverb": "- No longer stops the echo if the target dies\n",
    "Charged Shot": "- {{Icon|Grey Talon}} Grey Talon's {{Icon|Charged Shot}} Charged Shot effect matches the damage radius better\n",
    "Afterburn": "- {{Icon|Afterburn}} Afterburn T3 reduced from +40 dps to +35\n",
    "Ivy": "- {{Icon|Kudzu Bomb}} Kudzu Bomb T3 improved from +50 DPS to +60\n",
    "Ground Strike": "- Various fixes to {{Icon|Lash}} Lash's {{Icon|Ground Strike}} Ground Strike visual effects\n",
    "Paradox": "- Bullet base damage reduced from 8 to 7.2 (indirectly affects {{Icon|Kinetic Carbine}} Kinetic Carbine)\n- Bullet growth reduced from 0.48 to 0.42 (indirectly affects {{Icon|Kinetic Carbine}} Kinetic Carbine)\n- {{Icon|Kinetic Carbine}} Kinetic Carbine damage reduced from +100% to +85%\n- {{Icon|Paradox}} {{Icon|Paradoxical Swap}} Paradoxical Swap range reduced from 40m to 35m\n- Fixed {{Icon|Paradox}} {{Icon|Paradoxical Swap}} Paradoxical Swap being able to grab multiple heroes if they were really close to each other\n",
    "Kinetic Carbine": "- Bullet base damage reduced from 8 to 7.2 (indirectly affects {{Icon|Kinetic Carbine}} Kinetic Carbine)\n- Bullet growth reduced from 0.48 to 0.42 (indirectly affects {{Icon|Kinetic Carbine}} Kinetic Carbine)\n- {{Icon|Kinetic Carbine}} Kinetic Carbine damage reduced from +100% to +85%\n",
    "Warden": "- {{Icon|Willpower}} Willpower T1 improved from +15% to +20%\n- {{Icon|Last Stand}} Last Stand duration increased from 5s to 6s\n",
    "Last Stand": "- {{Icon|Last Stand}} Last Stand duration increased from 5s to 6s\n",
    "Headshot Booster": "- Cooldown reduced from 9s to 5s\n",
    "Ice Path": "- Players can now slide down the {{Icon|Ice Path}} Ice Path\n- {{Icon|Ice Path}} Ice Path slow resistance increased from 50% to 60%\n- {{Icon|Ice Path}} Ice Path T3 max spirit increased from 40 to 55\n",
    "Sleep Dagger": "- {{Icon|Sleep Dagger}} Sleep Dagger cooldown increased from 27 to 29\n- {{Icon|Sleep Dagger}} Sleep Dagger spirit scaling increased from 2.2 to 2.5\n",
    "Soul Exchange": "- {{Icon|Soul Exchange}} Soul Exchange cast time reduced from 0.5 to 0.2\n",
    "Flight": "- {{Icon|Flight}} Flight no longer grants +1 bonus air speed\n- {{Icon|Flight}} Flight falloff damage increase reduced from +20% to +10%\n",
    "Pulse Grenade": "- Fixed some sound issues with {{Icon|{{Icon|Pulse}} Pulse Grenade}} {{Icon|Pulse}} Pulse Grenade\n",
    "Pulse": "- Fixed some sound issues with {{Icon|{{Icon|Pulse}} Pulse Grenade}} {{Icon|Pulse}} Pulse Grenade\n",
    "Wraith": "- {{Icon|Project Mind}} Project Mind cooldown reduced from 50s to 45s\n",
    "Refresher": "- Spirit Resist increased from +10% to +12%\n",
    "Glass Cannon": "- Weapon Damage reduced from +70% to +65%\n",
    "Silencer": "- Ammo increased from +15% to +20%\n",
    "Leech": "- No longer gives +8 Spirit\n",
    "Kudzu Bomb": "- {{Icon|Kudzu Bomb}} Kudzu Bomb T3 improved from +50 DPS to +60\n",
    "Paradoxical Swap": "- {{Icon|Paradox}} {{Icon|Paradoxical Swap}} Paradoxical Swap range reduced from 40m to 35m\n- Fixed {{Icon|Paradox}} {{Icon|Paradoxical Swap}} Paradoxical Swap being able to grab multiple heroes if they were really close to each other\n",
    "Shadow Transformation": "- Fixed {{Icon|Power Slash}} Power Slash sometimes not being a full charge when channeled fully during the {{Icon|Shadow Transformation}} Shadow Transformation\n- {{Icon|Shadow Transformation}} Shadow Transformation's ability speedup now affects the post-cast durations as well\n- {{Icon|Shadow Transformation}} Shadow Transformation's ability speedup now improves the visual animations (cosmetic only change)\n",
    "Mystic Vulnerability": "- Fixed Turrets not proccing things like {{Icon|Mystic Vulnerability}} Mystic Vulnerability\n",
    "Assassinate": "- Added visual tell for when {{Icon|Assassinate}} Assassinate is active\n",
    "Basic Magazine": "- Ammo reduced from +16% to +15%\n- Weapon Damage reduced from +16% to +15%\n",
    "Enduring Spirit": "- No longer provides +1 Sprint\n- +10% {{Icon|Spirit Lifesteal}} Spirit Lifesteal\n",
    "Soul Shredder Bullets": "- Spirit Amp reduced from 14% to 12%\n",
    "Swift Striker": "- Bullet Resist penalty reduced from -8% to -7%\n",
    "Toxic Bullets": "- Now deals half damage against troopers and neutrals\n",
    "Spiritual Overflow": "- Spirit bonus increased from 30 to 35\n",
    "Boundless Spirit": "- Spirit increased from +40 to +45\n",
    "Seismic Impact": "- {{Icon|Seismic Impact}} Seismic Impact is now faster to play out\n- {{Icon|Seismic Impact}} Seismic Impact now has a very brief busy state upon landing\n",
    "Flame Dash": "- {{Icon|Flame Dash}} Flame Dash T1 duration reduced from 8s to 7s\n- {{Icon|Flame Dash}} Flame Dash T1 Fire Rate slow increased from +30% to +35%\n- {{Icon|Flame Dash}} Flame Dash T2 increased from +40 DPS to +45\n- {{Icon|Flame Dash}} Flame Dash T3 increased from -15s to -20s\n",
    "Metal Skin": "- Fixed flight spirit damage being able to pierce {{Icon|Metal Skin}} Metal Skin\n",
    "Willpower": "- {{Icon|Willpower}} Willpower T1 improved from +15% to +20%\n",
    "Project Mind": "- {{Icon|Project Mind}} Project Mind cooldown reduced from 50s to 45s\n"
}